xf_burn_tools/CRC.py
xf_burn_tools/__init__.py
xf_burn_tools/autoBurn.py
xf_burn_tools/burn_tools.py
xf_burn_tools/fwpkg.py
xf_burn_tools/pymodem.py
xf_burn_tools/ws63flash.py
xf_burn_tools-0.3.0.data/data/LICENSE
xf_burn_tools-0.3.0.dist-info/LICENSE
xf_burn_tools-0.3.0.dist-info/METADATA
xf_burn_tools-0.3.0.dist-info/WHEEL
xf_burn_tools-0.3.0.dist-info/entry_points.txt
xf_burn_tools-0.3.0.dist-info/top_level.txt
xf_burn_tools-0.3.0.dist-info/RECORD
